splx_proxy_sdk/__init__.py
splx_proxy_sdk/auth.py
splx_proxy_sdk/error.py
splx_proxy_sdk/logging.py
splx_proxy_sdk/model.py
splx_proxy_sdk/server.py
splx_proxy_sdk/version.py
splx_proxy_sdk-1.2.0.dist-info/LICENSE
splx_proxy_sdk-1.2.0.dist-info/METADATA
splx_proxy_sdk-1.2.0.dist-info/WHEEL
splx_proxy_sdk-1.2.0.dist-info/RECORD
