Metadata-Version: 2.1
Name: splx-proxy-sdk
Version: 1.2.0
Summary: SDK for building proxy servers for integration between user applications and the SPLX Platform
License: MIT
Author: Luka Simac
Author-email: luka.simac@splx.ai
Requires-Python: >=3.11,<4.0
Classifier: License :: OSI Approved :: MIT License
Classifier: Programming Language :: Python :: 3
Classifier: Programming Language :: Python :: 3.11
Classifier: Programming Language :: Python :: 3.12
Classifier: Programming Language :: Python :: 3.13
Requires-Dist: fastapi (>=0.116.1,<0.117.0)
Requires-Dist: loguru (>=0.7.2,<0.8.0)
Requires-Dist: pydantic (>=2.11.7,<3.0.0)
